winux/__init__.py
winux/winux.py
winux-1.1.3.dist-info/METADATA
winux-1.1.3.dist-info/WHEEL
winux-1.1.3.dist-info/entry_points.txt
winux-1.1.3.dist-info/top_level.txt
winux-1.1.3.dist-info/RECORD
