Metadata-Version: 2.1
Name: winux
Version: 1.1.3
Summary: UNKNOWN
Author: Cargo
License: UNKNOWN
Platform: UNKNOWN
Requires-Dist: click
